wdlcm/__init__.py
wdlcm/wdlcm.py
wdlcm-0.2.0.dist-info/LICENSE
wdlcm-0.2.0.dist-info/METADATA
wdlcm-0.2.0.dist-info/WHEEL
wdlcm-0.2.0.dist-info/entry_points.txt
wdlcm-0.2.0.dist-info/top_level.txt
wdlcm-0.2.0.dist-info/RECORD
