Metadata-Version: 2.1
Name: wdlcm
Version: 0.2.0
Summary: Simple tool to manager Warp10 data Life Cycle
Home-page: https://github.com/bubu11e/wdlcm
Author: Julien GIRARD
Author-email: julien.girard.ju@gmail.com
License: GPL3
Platform: UNKNOWN
Requires-Dist: requests
